colabtools/__init__.py
colabtools/gdrive.py
colabtools-0.0.1.dist-info/LICENSE
colabtools-0.0.1.dist-info/METADATA
colabtools-0.0.1.dist-info/WHEEL
colabtools-0.0.1.dist-info/top_level.txt
colabtools-0.0.1.dist-info/RECORD
