Metadata-Version: 2.1
Name: colabtools
Version: 0.0.1
Summary: Tools to work with colab from google
Home-page: https://github.com/zuuuhkrit/colabtools
Author: zuuuhkrit
Author-email: zuuuhkrit@gmail.com
License: UNKNOWN
Platform: UNKNOWN
Classifier: Programming Language :: Python :: 3
Classifier: License :: OSI Approved :: GNU Lesser General Public License v3 (LGPLv3)
Classifier: Operating System :: OS Independent
